{
  "app:open-settings": [
    {
      "modifiers": [
        "Alt",
        "Mod"
      ],
      "key": "S"
    }
  ],
  "file-explorer:reveal-active-file": [
    {
      "modifiers": [],
      "key": "F1"
    }
  ],
  "app:open-help": [],
  "workspace:goto-tab-1": [],
  "app:toggle-left-sidebar": [
    {
      "modifiers": [
        "Mod"
      ],
      "key": "1"
    }
  ],
  "command-palette:open": [
    {
      "modifiers": [
        "Mod",
        "Shift"
      ],
      "key": "A"
    }
  ]
}